Workbook
Name CategoryMaster: c_RevenuePVM!$A$2:$A$75
Name MonthList: i_Setup!$U$3:$U$14

Sheet i_Setup
B2: BUDGET VS ACTUAL VARIANCE ANALYSIS | U2: MonthList
U3: 42979
B4: Data Coverage & Known Limitations | U4: 43009
B5: Budget coverage begins Sep-2017 (no prior-year anchor before that) | U5: 43040
B6: Nov-2017 has no opex budget (YoY anchor month had zero delivered orders) | U6: 43070
B7: ~1.3% of revenue sits in an "uncategorized" bucket (immaterial) | U7: 43101
U8: 43132
B9: Controls | U9: 43160
B10: Select Month | C10: =o_Dashboard!C3 -> 43313 | U10: 43191
B11: $ Materiality Threshold | C11: 1000 | U11: 43221
B12: % Materiality Threshold | C12: 0.05 | U12: 43252
B13: Revenue $ Materiality Threshold | C13: 5000 | U13: 43282
U14: 43313
B15: Legend
B16: Favorable
B17: Unfavorable
B18: Flagged (breaches both thresholds)

Sheet i_Actuals
A1: month | B1: category | C1: revenue | D1: units | E1: avg_price
A2: 42614 | B2: health_beauty | C2: 134.97 | D2: 3 | E2: 44.99
A3: 42644 | B3: air_conditioning | C3: 1349.29 | D3: 8 | E3: 168.66125
A4: 42644 | B4: audio | C4: 156.99 | D4: 2 | E4: 78.495
A5: 42644 | B5: auto | C5: 1128.26 | D5: 8 | E5: 141.0325
A6: 42644 | B6: baby | C6: 1371.17 | D6: 11 | E6: 124.65182
A7: 42644 | B7: bed_bath_table | C7: 478.99 | D7: 8 | E7: 59.87375
A8: 42644 | B8: computers_accessories | C8: 669.02 | D8: 12 | E8: 55.751667
A9: 42644 | B9: consoles_games | C9: 3619.36 | D9: 7 | E9: 517.05143
A10: 42644 | B10: cool_stuff | C10: 1046.1 | D10: 7 | E10: 149.44286
A11: 42644 | B11: diapers_and_hygiene | C11: 134.9 | D11: 1 | E11: 134.9
A12: 42644 | B12: electronics | C12: 107.99 | D12: 1 | E12: 107.99
A13: 42644 | B13: fashio_female_clothing | C13: 54.9 | D13: 1 | E13: 54.9
... A1274: 43313 | B1274: watches_gifts | C1274: 69767.06 | D1274: 411 | E1274: 169.74954

Sheet i_Budget
A1: month | B1: category | C1: tier | D1: growth_rate | E1: budget_revenue | F1: budget_units | G1: budget_avg_price
A2: 42979 | B2: health_beauty | C2: mid | D2: 0.05 | E2: 141.7185 | F2: 3.15 | G2: 44.99
A3: 43009 | B3: air_conditioning | C3: mid | D3: 0.05 | E3: 1416.7545 | F3: 8.4 | G3: 168.66125
A4: 43009 | B4: audio | C4: high | D4: 0.1 | E4: 172.689 | F4: 2.2 | G4: 78.495
A5: 43009 | B5: auto | C5: mid | D5: 0.05 | E5: 1184.673 | F5: 8.4 | G5: 141.0325
A6: 43009 | B6: baby | C6: mid | D6: 0.05 | E6: 1439.7285 | F6: 11.55 | G6: 124.65182
A7: 43009 | B7: bed_bath_table | C7: low | D7: 0.02 | E7: 488.5698 | F7: 8.16 | G7: 59.87375
A8: 43009 | B8: computers_accessories | C8: high | D8: 0.1 | E8: 735.922 | F8: 13.2 | G8: 55.751667
A9: 43009 | B9: consoles_games | C9: high | D9: 0.1 | E9: 3981.296 | F9: 7.7 | G9: 517.05143
A10: 43009 | B10: cool_stuff | C10: mid | D10: 0.05 | E10: 1098.405 | F10: 7.35 | G10: 149.44286
A11: 43009 | B11: electronics | C11: high | D11: 0.1 | E11: 118.789 | F11: 1.1 | G11: 107.99
A12: 43009 | B12: fashion_bags_accessories | C12: mid | D12: 0.05 | E12: 391.965 | F12: 8.4 | G12: 46.6625
A13: 43009 | B13: fashion_male_clothing | C13: mid | D13: 0.05 | E13: 26.145 | F13: 1.05 | G13: 24.9
... A457: 43313 | B457: watches_gifts | C457: mid | D457: 0.05 | E457: 37979.497 | F457: 221.55 | G457: 171.4263

Sheet i_OpexActuals
A1: month | B1: line_item | C1: budget | D1: actual | E1: variance | F1: variance_pct
A2: 42979 | B2: ad_spend | C2: 8.50311 | D2: 8.58924 | E2: 0.086129963 | F2: 0.010129231
A3: 42979 | B3: logistics | C3: 14.175 | D3: 12.975556 | E3: -1.1994442 | F3: -0.084616874
A4: 42979 | B4: payroll | C4: 45000 | D4: 45447.043 | E4: 447.04274 | F4: 0.0099342831
A5: 42979 | B5: rent | C5: 8000 | D5: 7962.7416 | E5: -37.25838 | F5: -0.0046572975
A6: 43009 | B6: ad_spend | C6: 2523.9734 | D6: 1984.5694 | E6: -539.40398 | F6: -0.21371223
A7: 43009 | B7: logistics | C7: 1461.465 | D7: 1557.6346 | E7: 96.169648 | F7: 0.065803593
A8: 43009 | B8: payroll | C8: 45000 | D8: 44875.562 | E8: -124.43787 | F8: -0.002765286
A9: 43009 | B9: rent | C9: 8000 | D9: 8019.357 | E9: 19.356982 | F9: 0.0024196227
A10: 43070 | B10: ad_spend | C10: 0.6867 | D10: 0.63062586 | E10: -0.056074143 | F10: -0.081657409
A11: 43070 | B11: logistics | C11: 4.725 | D11: 4.2635211 | E11: -0.4614789 | F11: -0.097667492
A12: 43070 | B12: payroll | C12: 45000 | D12: 45582.92 | E12: 582.91968 | F12: 0.012953771
A13: 43070 | B13: rent | C13: 8000 | D13: 7846.9376 | E13: -153.06242 | F13: -0.019132802
... A45: 43313 | B45: rent | C45: 8000 | D45: 7981.9379 | E45: -18.062104 | F45: -0.002257763

Sheet c_RevenuePVM
A1: Category | B1: Budget Revenue | C1: Actual Revenue | D1: Budget Units | E1: Actual Units | F1: Budget Avg Price | G1: Actual Avg Price | H1: Total $ Variance | I1: Price Effect | J1: Volume Effect | K1: Check | L1: Status | M1: Flagged | N1: Rank
A2: agro_industry_and_commerce | B2: =SUMIFS(tbl_Budget[budget_revenue],tbl_Budget[category],$A2,tbl_Budget[month],i_Setup!$C$10) -> 92.4 | C2: =SUMIFS(tbl_Actuals[revenue],tbl_Actuals[category],$A2, tbl_Actuals[month],i_Setup!$C$10) -> 5021.09 | D2: =SUMIFS(tbl_Budget[budget_units],tbl_Budget[category],$A2,tbl_Budget[month],i_Setup!$C$10) -> 4.2 | E2: =SUMIFS(tbl_Actuals[units], tbl_Actuals[category], $A2, tbl_Actuals[month], i_Setup!$C$10) -> 18 | F2: =SUMIFS(tbl_Budget[budget_avg_price], tbl_Budget[category], $A2, tbl_Budget[month], i_Setup!$C$10) -> 22 | G2: =SUMIFS(tbl_Actuals[avg_price], tbl_Actuals[category], $A2, tbl_Actuals[month], i_Setup!$C$10) -> 278.94944 | H2: =C2-B2 -> 4928.69 | I2: =IF($B2=0,0,(G2-F2)*E2) -> 4625.09 | J2: =IF($B2=0,0,(E2-D2)*F2) -> 303.6 | K2: =IF($B2=0,"",ROUND(H2-I2-J2,2)) -> 0 | L2: =IF(AND(B2=0,C2=0),"No Activity",IF(B2=0,"Unbudgeted","")) | M2: =IF(L2="Unbudgeted",IF(H2>=i_Setup!$C$13,"FLAG",""),IF(L2="No Activity","",IF(AND(ABS(H2)>=i_Setup!$C$13,ABS(H2/B2)>=i_Setup!$C$12),"FLAG",""))) | N2: =IF(M2="FLAG",COUNTIF($M$2:M2,"FLAG"),"")
A3: air_conditioning | B3: =SUMIFS(tbl_Budget[budget_revenue],tbl_Budget[category],$A3,tbl_Budget[month],i_Setup!$C$10) -> 4485.3165 | C3: =SUMIFS(tbl_Actuals[revenue],tbl_Actuals[category],$A3, tbl_Actuals[month],i_Setup!$C$10) -> 3556.9 | D3: =SUMIFS(tbl_Budget[budget_units],tbl_Budget[category],$A3,tbl_Budget[month],i_Setup!$C$10) -> 15.75 | E3: =SUMIFS(tbl_Actuals[units], tbl_Actuals[category], $A3, tbl_Actuals[month], i_Setup!$C$10) -> 21 | F3: =SUMIFS(tbl_Budget[budget_avg_price], tbl_Budget[category], $A3, tbl_Budget[month], i_Setup!$C$10) -> 284.782 | G3: =SUMIFS(tbl_Actuals[avg_price], tbl_Actuals[category], $A3, tbl_Actuals[month], i_Setup!$C$10) -> 169.37619 | H3: =C3-B3 -> -928.4165 | I3: =IF($B3=0,0,(G3-F3)*E3) -> -2423.522 | J3: =IF($B3=0,0,(E3-D3)*F3) -> 1495.1055 | K3: =IF($B3=0,"",ROUND(H3-I3-J3,2)) -> 0 | L3: =IF(AND(B3=0,C3=0),"No Activity",IF(B3=0,"Unbudgeted","")) | M3: =IF(L3="Unbudgeted",IF(H3>=i_Setup!$C$13,"FLAG",""),IF(L3="No Activity","",IF(AND(ABS(H3)>=i_Setup!$C$13,ABS(H3/B3)>=i_Setup!$C$12),"FLAG",""))) | N3: =IF(M3="FLAG",COUNTIF($M$2:M3,"FLAG"),"")
A4: art | B4: =SUMIFS(tbl_Budget[budget_revenue],tbl_Budget[category],$A4,tbl_Budget[month],i_Setup!$C$10) -> 256.935 | C4: =SUMIFS(tbl_Actuals[revenue],tbl_Actuals[category],$A4, tbl_Actuals[month],i_Setup!$C$10) -> 1481.39 | D4: =SUMIFS(tbl_Budget[budget_units],tbl_Budget[category],$A4,tbl_Budget[month],i_Setup!$C$10) -> 4.2 | E4: =SUMIFS(tbl_Actuals[units], tbl_Actuals[category], $A4, tbl_Actuals[month], i_Setup!$C$10) -> 18 | F4: =SUMIFS(tbl_Budget[budget_avg_price], tbl_Budget[category], $A4, tbl_Budget[month], i_Setup!$C$10) -> 61.175 | G4: =SUMIFS(tbl_Actuals[avg_price], tbl_Actuals[category], $A4, tbl_Actuals[month], i_Setup!$C$10) -> 82.299444 | H4: =C4-B4 -> 1224.455 | I4: =IF($B4=0,0,(G4-F4)*E4) -> 380.23999 | J4: =IF($B4=0,0,(E4-D4)*F4) -> 844.215 | K4: =IF($B4=0,"",ROUND(H4-I4-J4,2)) -> 0 | L4: =IF(AND(B4=0,C4=0),"No Activity",IF(B4=0,"Unbudgeted","")) | M4: =IF(L4="Unbudgeted",IF(H4>=i_Setup!$C$13,"FLAG",""),IF(L4="No Activity","",IF(AND(ABS(H4)>=i_Setup!$C$13,ABS(H4/B4)>=i_Setup!$C$12),"FLAG",""))) | N4: =IF(M4="FLAG",COUNTIF($M$2:M4,"FLAG"),"")
A5: arts_and_craftmanship | B5: =SUMIFS(tbl_Budget[budget_revenue],tbl_Budget[category],$A5,tbl_Budget[month],i_Setup!$C$10) -> 0 | C5: =SUMIFS(tbl_Actuals[revenue],tbl_Actuals[category],$A5, tbl_Actuals[month],i_Setup!$C$10) -> 901.76 | D5: =SUMIFS(tbl_Budget[budget_units],tbl_Budget[category],$A5,tbl_Budget[month],i_Setup!$C$10) -> 0 | E5: =SUMIFS(tbl_Actuals[units], tbl_Actuals[category], $A5, tbl_Actuals[month], i_Setup!$C$10) -> 9 | F5: =SUMIFS(tbl_Budget[budget_avg_price], tbl_Budget[category], $A5, tbl_Budget[month], i_Setup!$C$10) -> 0 | G5: =SUMIFS(tbl_Actuals[avg_price], tbl_Actuals[category], $A5, tbl_Actuals[month], i_Setup!$C$10) -> 100.19556 | H5: =C5-B5 -> 901.76 | I5: =IF($B5=0,0,(G5-F5)*E5) -> 0 | J5: =IF($B5=0,0,(E5-D5)*F5) -> 0 | K5: =IF($B5=0,"",ROUND(H5-I5-J5,2)) | L5: =IF(AND(B5=0,C5=0),"No Activity",IF(B5=0,"Unbudgeted","")) -> Unbudgeted | M5: =IF(L5="Unbudgeted",IF(H5>=i_Setup!$C$13,"FLAG",""),IF(L5="No Activity","",IF(AND(ABS(H5)>=i_Setup!$C$13,ABS(H5/B5)>=i_Setup!$C$12),"FLAG",""))) | N5: =IF(M5="FLAG",COUNTIF($M$2:M5,"FLAG"),"")
A6: audio | B6: =SUMIFS(tbl_Budget[budget_revenue],tbl_Budget[category],$A6,tbl_Budget[month],i_Setup!$C$10) -> 1155.77 | C6: =SUMIFS(tbl_Actuals[revenue],tbl_Actuals[category],$A6, tbl_Actuals[month],i_Setup!$C$10) -> 2069.4 | D6: =SUMIFS(tbl_Budget[budget_units],tbl_Budget[category],$A6,tbl_Budget[month],i_Setup!$C$10) -> 7.7 | E6: =SUMIFS(tbl_Actuals[units], tbl_Actuals[category], $A6, tbl_Actuals[month], i_Setup!$C$10) -> 26 | F6: =SUMIFS(tbl_Budget[budget_avg_price], tbl_Budget[category], $A6, tbl_Budget[month], i_Setup!$C$10) -> 150.1 | G6: =SUMIFS(tbl_Actuals[avg_price], tbl_Actuals[category], $A6, tbl_Actuals[month], i_Setup!$C$10) -> 79.592308 | H6: =C6-B6 -> 913.63 | I6: =IF($B6=0,0,(G6-F6)*E6) -> -1833.2 | J6: =IF($B6=0,0,(E6-D6)*F6) -> 2746.83 | K6: =IF($B6=0,"",ROUND(H6-I6-J6,2)) -> 0 | L6: =IF(AND(B6=0,C6=0),"No Activity",IF(B6=0,"Unbudgeted","")) | M6: =IF(L6="Unbudgeted",IF(H6>=i_Setup!$C$13,"FLAG",""),IF(L6="No Activity","",IF(AND(ABS(H6)>=i_Setup!$C$13,ABS(H6/B6)>=i_Setup!$C$12),"FLAG",""))) | N6: =IF(M6="FLAG",COUNTIF($M$2:M6,"FLAG"),"")
A7: auto | B7: =SUMIFS(tbl_Budget[budget_revenue],tbl_Budget[category],$A7,tbl_Budget[month],i_Setup!$C$10) -> 19868.74 | C7: =SUMIFS(tbl_Actuals[revenue],tbl_Actuals[category],$A7, tbl_Actuals[month],i_Setup!$C$10) -> 45032.58 | D7: =SUMIFS(tbl_Budget[budget_units],tbl_Budget[category],$A7,tbl_Budget[month],i_Setup!$C$10) -> 169.05 | E7: =SUMIFS(tbl_Actuals[units], tbl_Actuals[category], $A7, tbl_Actuals[month], i_Setup!$C$10) -> 370 | F7: =SUMIFS(tbl_Budget[budget_avg_price], tbl_Budget[category], $A7, tbl_Budget[month], i_Setup!$C$10) -> 117.53174 | G7: =SUMIFS(tbl_Actuals[avg_price], tbl_Actuals[category], $A7, tbl_Actuals[month], i_Setup!$C$10) -> 121.70968 | H7: =C7-B7 -> 25163.84 | I7: =IF($B7=0,0,(G7-F7)*E7) -> 1545.8366 | J7: =IF($B7=0,0,(E7-D7)*F7) -> 23618.003 | K7: =IF($B7=0,"",ROUND(H7-I7-J7,2)) -> 0 | L7: =IF(AND(B7=0,C7=0),"No Activity",IF(B7=0,"Unbudgeted","")) | M7: =IF(L7="Unbudgeted",IF(H7>=i_Setup!$C$13,"FLAG",""),IF(L7="No Activity","",IF(AND(ABS(H7)>=i_Setup!$C$13,ABS(H7/B7)>=i_Setup!$C$12),"FLAG",""))) -> FLAG | N7: =IF(M7="FLAG",COUNTIF($M$2:M7,"FLAG"),"") -> 1
A8: baby | B8: =SUMIFS(tbl_Budget[budget_revenue],tbl_Budget[category],$A8,tbl_Budget[month],i_Setup!$C$10) -> 20118.105 | C8: =SUMIFS(tbl_Actuals[revenue],tbl_Actuals[category],$A8, tbl_Actuals[month],i_Setup!$C$10) -> 21266.57 | D8: =SUMIFS(tbl_Budget[budget_units],tbl_Budget[category],$A8,tbl_Budget[month],i_Setup!$C$10) -> 133.35 | E8: =SUMIFS(tbl_Actuals[units], tbl_Actuals[category], $A8, tbl_Actuals[month], i_Setup!$C$10) -> 212 | F8: =SUMIFS(tbl_Budget[budget_avg_price], tbl_Budget[category], $A8, tbl_Budget[month], i_Setup!$C$10) -> 150.86693 | G8: =SUMIFS(tbl_Actuals[avg_price], tbl_Actuals[category], $A8, tbl_Actuals[month], i_Setup!$C$10) -> 100.31401 | H8: =C8-B8 -> 1148.465 | I8: =IF($B8=0,0,(G8-F8)*E8) -> -10717.219 | J8: =IF($B8=0,0,(E8-D8)*F8) -> 11865.684 | K8: =IF($B8=0,"",ROUND(H8-I8-J8,2)) -> 0 | L8: =IF(AND(B8=0,C8=0),"No Activity",IF(B8=0,"Unbudgeted","")) | M8: =IF(L8="Unbudgeted",IF(H8>=i_Setup!$C$13,"FLAG",""),IF(L8="No Activity","",IF(AND(ABS(H8)>=i_Setup!$C$13,ABS(H8/B8)>=i_Setup!$C$12),"FLAG",""))) | N8: =IF(M8="FLAG",COUNTIF($M$2:M8,"FLAG"),"")
A9: bed_bath_table | B9: =SUMIFS(tbl_Budget[budget_revenue],tbl_Budget[category],$A9,tbl_Budget[month],i_Setup!$C$10) -> 57712.243 | C9: =SUMIFS(tbl_Actuals[revenue],tbl_Actuals[category],$A9, tbl_Actuals[month],i_Setup!$C$10) -> 60891.09 | D9: =SUMIFS(tbl_Budget[budget_units],tbl_Budget[category],$A9,tbl_Budget[month],i_Setup!$C$10) -> 516.12 | E9: =SUMIFS(tbl_Actuals[units], tbl_Actuals[category], $A9, tbl_Actuals[month], i_Setup!$C$10) -> 655 | F9: =SUMIFS(tbl_Budget[budget_avg_price], tbl_Budget[category], $A9, tbl_Budget[month], i_Setup!$C$10) -> 111.81943 | G9: =SUMIFS(tbl_Actuals[avg_price], tbl_Actuals[category], $A9, tbl_Actuals[month], i_Setup!$C$10) -> 92.963496 | H9: =C9-B9 -> 3178.8474 | I9: =IF($B9=0,0,(G9-F9)*E9) -> -12350.635 | J9: =IF($B9=0,0,(E9-D9)*F9) -> 15529.482 | K9: =IF($B9=0,"",ROUND(H9-I9-J9,2)) -> 0 | L9: =IF(AND(B9=0,C9=0),"No Activity",IF(B9=0,"Unbudgeted","")) | M9: =IF(L9="Unbudgeted",IF(H9>=i_Setup!$C$13,"FLAG",""),IF(L9="No Activity","",IF(AND(ABS(H9)>=i_Setup!$C$13,ABS(H9/B9)>=i_Setup!$C$12),"FLAG",""))) | N9: =IF(M9="FLAG",COUNTIF($M$2:M9,"FLAG"),"")
A10: books_general_interest | B10: =SUMIFS(tbl_Budget[budget_revenue],tbl_Budget[category],$A10,tbl_Budget[month],i_Setup!$C$10) -> 2388.75 | C10: =SUMIFS(tbl_Actuals[revenue],tbl_Actuals[category],$A10, tbl_Actuals[month],i_Setup!$C$10) -> 1564.78 | D10: =SUMIFS(tbl_Budget[budget_units],tbl_Budget[category],$A10,tbl_Budget[month],i_Setup!$C$10) -> 28.35 | E10: =SUMIFS(tbl_Actuals[units], tbl_Actuals[category], $A10, tbl_Actuals[month], i_Setup!$C$10) -> 36 | F10: =SUMIFS(tbl_Budget[budget_avg_price], tbl_Budget[category], $A10, tbl_Budget[month], i_Setup!$C$10) -> 84.259259 | G10: =SUMIFS(tbl_Actuals[avg_price], tbl_Actuals[category], $A10, tbl_Actuals[month], i_Setup!$C$10) -> 43.466111 | H10: =C10-B10 -> -823.97 | I10: =IF($B10=0,0,(G10-F10)*E10) -> -1468.5533 | J10: =IF($B10=0,0,(E10-D10)*F10) -> 644.58333 | K10: =IF($B10=0,"",ROUND(H10-I10-J10,2)) -> 0 | L10: =IF(AND(B10=0,C10=0),"No Activity",IF(B10=0,"Unbudgeted","")) | M10: =IF(L10="Unbudgeted",IF(H10>=i_Setup!$C$13,"FLAG",""),IF(L10="No Activity","",IF(AND(ABS(H10)>=i_Setup!$C$13,ABS(H10/B10)>=i_Setup!$C$12),"FLAG",""))) | N10: =IF(M10="FLAG",COUNTIF($M$2:M10,"FLAG"),"")
A11: books_imported | B11: =SUMIFS(tbl_Budget[budget_revenue],tbl_Budget[category],$A11,tbl_Budget[month],i_Setup!$C$10) -> 64.05 | C11: =SUMIFS(tbl_Actuals[revenue],tbl_Actuals[category],$A11, tbl_Actuals[month],i_Setup!$C$10) -> 749 | D11: =SUMIFS(tbl_Budget[budget_units],tbl_Budget[category],$A11,tbl_Budget[month],i_Setup!$C$10) -> 1.05 | E11: =SUMIFS(tbl_Actuals[units], tbl_Actuals[category], $A11, tbl_Actuals[month], i_Setup!$C$10) -> 1 | F11: =SUMIFS(tbl_Budget[budget_avg_price], tbl_Budget[category], $A11, tbl_Budget[month], i_Setup!$C$10) -> 61 | G11: =SUMIFS(tbl_Actuals[avg_price], tbl_Actuals[category], $A11, tbl_Actuals[month], i_Setup!$C$10) -> 749 | H11: =C11-B11 -> 684.95 | I11: =IF($B11=0,0,(G11-F11)*E11) -> 688 | J11: =IF($B11=0,0,(E11-D11)*F11) -> -3.05 | K11: =IF($B11=0,"",ROUND(H11-I11-J11,2)) -> 0 | L11: =IF(AND(B11=0,C11=0),"No Activity",IF(B11=0,"Unbudgeted","")) | M11: =IF(L11="Unbudgeted",IF(H11>=i_Setup!$C$13,"FLAG",""),IF(L11="No Activity","",IF(AND(ABS(H11)>=i_Setup!$C$13,ABS(H11/B11)>=i_Setup!$C$12),"FLAG",""))) | N11: =IF(M11="FLAG",COUNTIF($M$2:M11,"FLAG"),"")
A12: books_technical | B12: =SUMIFS(tbl_Budget[budget_revenue],tbl_Budget[category],$A12,tbl_Budget[month],i_Setup!$C$10) -> 1256.199 | C12: =SUMIFS(tbl_Actuals[revenue],tbl_Actuals[category],$A12, tbl_Actuals[month],i_Setup!$C$10) -> 1483.79 | D12: =SUMIFS(tbl_Budget[budget_units],tbl_Budget[category],$A12,tbl_Budget[month],i_Setup!$C$10) -> 9.45 | E12: =SUMIFS(tbl_Actuals[units], tbl_Actuals[category], $A12, tbl_Actuals[month], i_Setup!$C$10) -> 29 | F12: =SUMIFS(tbl_Budget[budget_avg_price], tbl_Budget[category], $A12, tbl_Budget[month], i_Setup!$C$10) -> 132.93111 | G12: =SUMIFS(tbl_Actuals[avg_price], tbl_Actuals[category], $A12, tbl_Actuals[month], i_Setup!$C$10) -> 51.165172 | H12: =C12-B12 -> 227.591 | I12: =IF($B12=0,0,(G12-F12)*E12) -> -2371.2122 | J12: =IF($B12=0,0,(E12-D12)*F12) -> 2598.8032 | K12: =IF($B12=0,"",ROUND(H12-I12-J12,2)) -> 0 | L12: =IF(AND(B12=0,C12=0),"No Activity",IF(B12=0,"Unbudgeted","")) | M12: =IF(L12="Unbudgeted",IF(H12>=i_Setup!$C$13,"FLAG",""),IF(L12="No Activity","",IF(AND(ABS(H12)>=i_Setup!$C$13,ABS(H12/B12)>=i_Setup!$C$12),"FLAG",""))) | N12: =IF(M12="FLAG",COUNTIF($M$2:M12,"FLAG"),"")
A13: cds_dvds_musicals | B13: =SUMIFS(tbl_Budget[budget_revenue],tbl_Budget[category],$A13,tbl_Budget[month],i_Setup!$C$10) -> 0 | C13: =SUMIFS(tbl_Actuals[revenue],tbl_Actuals[category],$A13, tbl_Actuals[month],i_Setup!$C$10) -> 0 | D13: =SUMIFS(tbl_Budget[budget_units],tbl_Budget[category],$A13,tbl_Budget[month],i_Setup!$C$10) -> 0 | E13: =SUMIFS(tbl_Actuals[units], tbl_Actuals[category], $A13, tbl_Actuals[month], i_Setup!$C$10) -> 0 | F13: =SUMIFS(tbl_Budget[budget_avg_price], tbl_Budget[category], $A13, tbl_Budget[month], i_Setup!$C$10) -> 0 | G13: =SUMIFS(tbl_Actuals[avg_price], tbl_Actuals[category], $A13, tbl_Actuals[month], i_Setup!$C$10) -> 0 | H13: =C13-B13 -> 0 | I13: =IF($B13=0,0,(G13-F13)*E13) -> 0 | J13: =IF($B13=0,0,(E13-D13)*F13) -> 0 | K13: =IF($B13=0,"",ROUND(H13-I13-J13,2)) | L13: =IF(AND(B13=0,C13=0),"No Activity",IF(B13=0,"Unbudgeted","")) -> No Activity | M13: =IF(L13="Unbudgeted",IF(H13>=i_Setup!$C$13,"FLAG",""),IF(L13="No Activity","",IF(AND(ABS(H13)>=i_Setup!$C$13,ABS(H13/B13)>=i_Setup!$C$12),"FLAG",""))) | N13: =IF(M13="FLAG",COUNTIF($M$2:M13,"FLAG"),"")
... A75: watches_gifts | B75: =SUMIFS(tbl_Budget[budget_revenue],tbl_Budget[category],$A75,tbl_Budget[month],i_Setup!$C$10) -> 37979.497 | C75: =SUMIFS(tbl_Actuals[revenue],tbl_Actuals[category],$A75, tbl_Actuals[month],i_Setup!$C$10) -> 69767.06 | D75: =SUMIFS(tbl_Budget[budget_units],tbl_Budget[category],$A75,tbl_Budget[month],i_Setup!$C$10) -> 221.55 | E75: =SUMIFS(tbl_Actuals[units], tbl_Actuals[category], $A75, tbl_Actuals[month], i_Setup!$C$10) -> 411 | F75: =SUMIFS(tbl_Budget[budget_avg_price], tbl_Budget[category], $A75, tbl_Budget[month], i_Setup!$C$10) -> 171.4263 | G75: =SUMIFS(tbl_Actuals[avg_price], tbl_Actuals[category], $A75, tbl_Actuals[month], i_Setup!$C$10) -> 169.74954 | H75: =C75-B75 -> 31787.562 | I75: =IF($B75=0,0,(G75-F75)*E75) -> -689.15055 | J75: =IF($B75=0,0,(E75-D75)*F75) -> 32476.713 | K75: =IF($B75=0,"",ROUND(H75-I75-J75,2)) -> 0 | L75: =IF(AND(B75=0,C75=0),"No Activity",IF(B75=0,"Unbudgeted","")) | M75: =IF(L75="Unbudgeted",IF(H75>=i_Setup!$C$13,"FLAG",""),IF(L75="No Activity","",IF(AND(ABS(H75)>=i_Setup!$C$13,ABS(H75/B75)>=i_Setup!$C$12),"FLAG",""))) -> FLAG | N75: =IF(M75="FLAG",COUNTIF($M$2:M75,"FLAG"),"") -> 18
A76: TOTAL | B76: =SUM(B2:B75) -> 579864.95 | C76: =SUM(C2:C75) -> 838576.64 | D76: =SUM(D2:D75) -> 4996.56 | E76: =SUM(E2:E75) -> 7142 | H76: =SUM(H2:H75) -> 258711.69 | I76: =SUM(I2:I75) -> 21112.123 | J76: =SUM(J2:J75) -> 230809.16 | K76: =H76-I76-J76 -> 6790.4095 | L76: Mix/Unbudgeted Effect | N76: =ROUND(H76-I76-J76-K76,2) -> 0

Sheet c_OpexFlux
A1: Opex Flux Analysis - Selected Month: | B1: =i_Setup!$C$10 -> 43313
A3: Line Item | B3: Budget | C3: Actual | D3: $ Variance | E3: % Variance | F3: Status | G3: Flagged
A4: payroll | B4: =SUMIFS(tbl_Opex[budget],tbl_Opex[line_item],$A4,tbl_Opex[month],i_Setup!$C$10) -> 45000 | C4: =SUMIFS(tbl_Opex[actual],tbl_Opex[line_item],$A4,tbl_Opex[month],i_Setup!$C$10) -> 44582.924 | D4: =IF(AND(B4=0,C4=0),"",C4-B4) -> -417.07592 | E4: =IF(AND(B4=0,C4=0),"",IF(B4=0,"",D4/B4)) -> -0.0092683539 | F4: =IF(AND(B4=0,C4=0),"No Data — Nov-2017 excluded (YoY anchor had zero delivered orders)","") | G4: =IF(F4<>"","",IF(AND(ABS(D4)>=i_Setup!$C$11,ABS(E4)>=i_Setup!$C$12),"FLAG",""))
A5: rent | B5: =SUMIFS(tbl_Opex[budget],tbl_Opex[line_item],$A5,tbl_Opex[month],i_Setup!$C$10) -> 8000 | C5: =SUMIFS(tbl_Opex[actual],tbl_Opex[line_item],$A5,tbl_Opex[month],i_Setup!$C$10) -> 7981.9379 | D5: =IF(AND(B5=0,C5=0),"",C5-B5) -> -18.062104 | E5: =IF(AND(B5=0,C5=0),"",IF(B5=0,"",D5/B5)) -> -0.002257763 | F5: =IF(AND(B5=0,C5=0),"No Data — Nov-2017 excluded (YoY anchor had zero delivered orders)","") | G5: =IF(F5<>"","",IF(AND(ABS(D5)>=i_Setup!$C$11,ABS(E5)>=i_Setup!$C$12),"FLAG",""))
A6: ad_spend | B6: =SUMIFS(tbl_Opex[budget],tbl_Opex[line_item],$A6,tbl_Opex[month],i_Setup!$C$10) -> 34791.897 | C6: =SUMIFS(tbl_Opex[actual],tbl_Opex[line_item],$A6,tbl_Opex[month],i_Setup!$C$10) -> 34721.458 | D6: =IF(AND(B6=0,C6=0),"",C6-B6) -> -70.439107 | E6: =IF(AND(B6=0,C6=0),"",IF(B6=0,"",D6/B6)) -> -0.0020245837 | F6: =IF(AND(B6=0,C6=0),"No Data — Nov-2017 excluded (YoY anchor had zero delivered orders)","") | G6: =IF(F6<>"","",IF(AND(ABS(D6)>=i_Setup!$C$11,ABS(E6)>=i_Setup!$C$12),"FLAG",""))
A7: logistics | B7: =SUMIFS(tbl_Opex[budget],tbl_Opex[line_item],$A7,tbl_Opex[month],i_Setup!$C$10) -> 22484.52 | C7: =SUMIFS(tbl_Opex[actual],tbl_Opex[line_item],$A7,tbl_Opex[month],i_Setup!$C$10) -> 21942.906 | D7: =IF(AND(B7=0,C7=0),"",C7-B7) -> -541.61377 | E7: =IF(AND(B7=0,C7=0),"",IF(B7=0,"",D7/B7)) -> -0.024088296 | F7: =IF(AND(B7=0,C7=0),"No Data — Nov-2017 excluded (YoY anchor had zero delivered orders)","") | G7: =IF(F7<>"","",IF(AND(ABS(D7)>=i_Setup!$C$11,ABS(E7)>=i_Setup!$C$12),"FLAG",""))

Sheet o_Dashboard
B2: BUDGET VS ACTUAL VARIANCE DASHBOARD
B3: Select Month: | C3: 43313
B5: Total Revenue Variance | D5: OpEx Variance | F5: Flagged Categories | H5: Flagged OpEx Lines | J5: Uncategorized %
B7: =c_RevenuePVM!H76 -> 258711.69 | D7: =SUM(c_OpexFlux!D4:D7) -> -1047.1909 | F7: =c_RevenuePVM!P2 -> 0 | H7: =COUNTIF(c_OpexFlux!G4:G7,"FLAG") -> 0 | J7: 0.013
B8: =(B7/c_RevenuePVM!B76) -> 0.44615853
B10: Monthly Trend
B11: Month | C11: Budget Revenue | D11: Actual Revenue | E11: Variance %
B12: 42979 | C12: =SUMIFS(tbl_Budget[budget_revenue],tbl_Budget[month],B12) -> 141.7185 | D12: =SUMIFS(tbl_Actuals[revenue],tbl_Actuals[month],B12) -> 607399.67 | E12: =IF(C12=0,"",(D12-C12)/C12) -> 4284.9589
B13: 43009 | C13: =SUMIFS(tbl_Budget[budget_revenue],tbl_Budget[month],B13) -> 42066.223 | D13: =SUMIFS(tbl_Actuals[revenue],tbl_Actuals[month],B13) -> 648247.65 | E13: =IF(C13=0,"",(D13-C13)/C13) -> 14.41017
B14: 43040 | C14: =SUMIFS(tbl_Budget[budget_revenue],tbl_Budget[month],B14) -> 0 | D14: =SUMIFS(tbl_Actuals[revenue],tbl_Actuals[month],B14) -> 987765.37 | E14: =IF(C14=0,"N/A",(D14-C14)/C14) -> N/A
B15: 43070 | C15: =SUMIFS(tbl_Budget[budget_revenue],tbl_Budget[month],B15) -> 11.445 | D15: =SUMIFS(tbl_Actuals[revenue],tbl_Actuals[month],B15) -> 726033.19 | E15: =IF(C15=0,"",(D15-C15)/C15) -> 63435.714
B16: 43101 | C16: =SUMIFS(tbl_Budget[budget_revenue],tbl_Budget[month],B16) -> 116733.09 | D16: =SUMIFS(tbl_Actuals[revenue],tbl_Actuals[month],B16) -> 924645 | E16: =IF(C16=0,"",(D16-C16)/C16) -> 6.9210188
B17: 43132 | C17: =SUMIFS(tbl_Budget[budget_revenue],tbl_Budget[month],B17) -> 240801.44 | D17: =SUMIFS(tbl_Actuals[revenue],tbl_Actuals[month],B17) -> 826437.13 | E17: =IF(C17=0,"",(D17-C17)/C17) -> 2.4320274
B18: 43160 | C18: =SUMIFS(tbl_Budget[budget_revenue],tbl_Budget[month],B18) -> 375671.01 | D18: =SUMIFS(tbl_Actuals[revenue],tbl_Actuals[month],B18) -> 953356.25 | E18: =IF(C18=0,"",(D18-C18)/C18) -> 1.5377424
B19: 43191 | C19: =SUMIFS(tbl_Budget[budget_revenue],tbl_Budget[month],B19) -> 355963.85 | D19: =SUMIFS(tbl_Actuals[revenue],tbl_Actuals[month],B19) -> 973534.09 | E19: =IF(C19=0,"",(D19-C19)/C19) -> 1.7349241
B20: 43221 | C20: =SUMIFS(tbl_Budget[budget_revenue],tbl_Budget[month],B20) -> 511314.39 | D20: =SUMIFS(tbl_Actuals[revenue],tbl_Actuals[month],B20) -> 977544.69 | E20: =IF(C20=0,"",(D20-C20)/C20) -> 0.91182705
B21: 43252 | C21: =SUMIFS(tbl_Budget[budget_revenue],tbl_Budget[month],B21) -> 441279.48 | D21: =SUMIFS(tbl_Actuals[revenue],tbl_Actuals[month],B21) -> 856077.86 | E21: =IF(C21=0,"",(D21-C21)/C21) -> 0.93999019
B22: 43282 | C22: =SUMIFS(tbl_Budget[budget_revenue],tbl_Budget[month],B22) -> 502127.62 | D22: =SUMIFS(tbl_Actuals[revenue],tbl_Actuals[month],B22) -> 867953.46 | E22: =IF(C22=0,"",(D22-C22)/C22) -> 0.72855152
B23: 43313 | C23: =SUMIFS(tbl_Budget[budget_revenue],tbl_Budget[month],B23) -> 579864.95 | D23: =SUMIFS(tbl_Actuals[revenue],tbl_Actuals[month],B23) -> 838576.64 | E23: =IF(C23=0,"",(D23-C23)/C23) -> 0.44615853
B25: Sept-2017 through Dec-2017 excluded from trend — budget coverage too thin (1, 28, 0, and 1 categories respectively) for a whole-month variance % to be meaningful. Jan-2018 also shows an unusually high variance (~692%) due to thin early-period budget coverage; treat with the same caution. See i_Setup for full data coverage notes.

Sheet o_VarianceBridge
A1: ="Revenue Bridge - "&TEXT(i_Setup!$C$10,"mmm-yyyy") -> Revenue Bridge - Aug-2018
A3: Stage | B3: Value
A4: Budget Revenue | B4: =c_RevenuePVM!B76 -> 579864.95
A5: Price Effect | B5: =c_RevenuePVM!I76 -> 21112.123
A6: Volume Effect | B6: =c_RevenuePVM!J76 -> 230809.16
A7: Mix/Unbudgeted | B7: =c_RevenuePVM!K76 -> 6790.4095
A8: Actual Revenue | B8: =c_RevenuePVM!C76 -> 838576.64
A10: ="OpEx $ Variance - "&TEXT(i_Setup!$C$10,"mmm-yyyy") -> OpEx $ Variance - Aug-2018
A12: Line Item | B12: $ Variance
A13: Payroll | B13: =c_OpexFlux!D4 -> -417.07592
A14: Rent | B14: =c_OpexFlux!D5 -> -18.062104
A15: Ad Spend | B15: =c_OpexFlux!D6 -> -70.439107
A16: Logistics | B16: =c_OpexFlux!D7 -> -541.61377

Sheet o_FluxCommentary
A1: Flux Commentary - Selected Month: | B1: =i_Setup!C10 -> 43313
A3: Source | B3: Line/Category | C3: Budget | D3: Actual | E3: $ Variance | F3: % Variance | G3: Direction | H3: Commentary
A4: =IF(c_OpexFlux!G4="FLAG","OpEx","") | B4: =IF(c_OpexFlux!G4="FLAG",c_OpexFlux!A4,"") | C4: =IF(c_OpexFlux!G4="FLAG",c_OpexFlux!B4,"") | D4: =IF(c_OpexFlux!G4="FLAG",c_OpexFlux!C4,"") | E4: =IF(c_OpexFlux!G4="FLAG",c_OpexFlux!D4,"") | F4: =IF(c_OpexFlux!G4="FLAG",c_OpexFlux!E4,"") | G4: =IF(c_OpexFlux!G4="FLAG",IF(c_OpexFlux!D4>0,"Unfavorable","Favorable"),"")
A5: =IF(c_OpexFlux!G5="FLAG","OpEx","") | B5: =IF(c_OpexFlux!G5="FLAG",c_OpexFlux!A5,"") | C5: =IF(c_OpexFlux!G5="FLAG",c_OpexFlux!B5,"") | D5: =IF(c_OpexFlux!G5="FLAG",c_OpexFlux!C5,"") | E5: =IF(c_OpexFlux!G5="FLAG",c_OpexFlux!D5,"") | F5: =IF(c_OpexFlux!G5="FLAG",c_OpexFlux!E5,"") | G5: =IF(c_OpexFlux!G5="FLAG",IF(c_OpexFlux!D5>0,"Unfavorable","Favorable"),"") | H5: =IF(c_OpexFlux!N5="FLAG","OpEx","")
A6: =IF(c_OpexFlux!G6="FLAG","OpEx","") | B6: =IF(c_OpexFlux!G6="FLAG",c_OpexFlux!A6,"") | C6: =IF(c_OpexFlux!G6="FLAG",c_OpexFlux!B6,"") | D6: =IF(c_OpexFlux!G6="FLAG",c_OpexFlux!C6,"") | E6: =IF(c_OpexFlux!G6="FLAG",c_OpexFlux!D6,"") | F6: =IF(c_OpexFlux!G6="FLAG",c_OpexFlux!E6,"") | G6: =IF(c_OpexFlux!G6="FLAG",IF(c_OpexFlux!D6>0,"Unfavorable","Favorable"),"") | H6: =IF(c_OpexFlux!N6="FLAG","OpEx","")
A7: =IF(c_OpexFlux!G7="FLAG","OpEx","") | B7: =IF(c_OpexFlux!G7="FLAG",c_OpexFlux!A7,"") | C7: =IF(c_OpexFlux!G7="FLAG",c_OpexFlux!B7,"") | D7: =IF(c_OpexFlux!G7="FLAG",c_OpexFlux!C7,"") | E7: =IF(c_OpexFlux!G7="FLAG",c_OpexFlux!D7,"") | F7: =IF(c_OpexFlux!G7="FLAG",c_OpexFlux!E7,"") | G7: =IF(c_OpexFlux!G7="FLAG",IF(c_OpexFlux!D7>0,"Unfavorable","Favorable"),"") | H7: =IF(c_OpexFlux!N7="FLAG","OpEx","")
A8: =IF(B8<>"","Revenue","") -> Revenue | B8: =IFERROR(INDEX(c_RevenuePVM!$A$2:$A$75,MATCH(ROWS($B$8:B8),c_RevenuePVM!$N$2:$N$75,0)),"") -> auto | C8: =IF($B8="","",SUMIFS(tbl_Budget[budget_revenue],tbl_Budget[category],$B8,tbl_Budget[month],i_Setup!$C$10)) -> 19868.74 | D8: =IF($B8="","",SUMIFS(tbl_Actuals[revenue],tbl_Actuals[category],$B8,tbl_Actuals[month],i_Setup!$C$10)) -> 45032.58 | E8: =IF($B8="","",D8-C8) -> 25163.84 | F8: =IF($B8="","",IF(C8=0,"",E8/C8)) -> 1.266504 | G8: =IF($B8="","",IF(E8>0,"Favorable","Unfavorable")) -> Favorable
A9: =IF(B9<>"","Revenue","") -> Revenue | B9: =IFERROR(INDEX(c_RevenuePVM!$A$2:$A$75,MATCH(ROWS($B$8:B9),c_RevenuePVM!$N$2:$N$75,0)),"") -> computers | C9: =IF($B9="","",SUMIFS(tbl_Budget[budget_revenue],tbl_Budget[category],$B9,tbl_Budget[month],i_Setup!$C$10)) -> 35640 | D9: =IF($B9="","",SUMIFS(tbl_Actuals[revenue],tbl_Actuals[category],$B9,tbl_Actuals[month],i_Setup!$C$10)) -> 8711.5 | E9: =IF($B9="","",D9-C9) -> -26928.5 | F9: =IF($B9="","",IF(C9=0,"",E9/C9)) -> -0.75556958 | G9: =IF($B9="","",IF(E9>0,"Favorable","Unfavorable")) -> Unfavorable
A10: =IF(B10<>"","Revenue","") -> Revenue | B10: =IFERROR(INDEX(c_RevenuePVM!$A$2:$A$75,MATCH(ROWS($B$8:B10),c_RevenuePVM!$N$2:$N$75,0)),"") -> construction_tools_construction | C10: =IF($B10="","",SUMIFS(tbl_Budget[budget_revenue],tbl_Budget[category],$B10,tbl_Budget[month],i_Setup!$C$10)) -> 1203.6 | D10: =IF($B10="","",SUMIFS(tbl_Actuals[revenue],tbl_Actuals[category],$B10,tbl_Actuals[month],i_Setup!$C$10)) -> 22917.16 | E10: =IF($B10="","",D10-C10) -> 21713.56 | F10: =IF($B10="","",IF(C10=0,"",E10/C10)) -> 18.040512 | G10: =IF($B10="","",IF(E10>0,"Favorable","Unfavorable")) -> Favorable
A11: =IF(B11<>"","Revenue","") -> Revenue | B11: =IFERROR(INDEX(c_RevenuePVM!$A$2:$A$75,MATCH(ROWS($B$8:B11),c_RevenuePVM!$N$2:$N$75,0)),"") -> construction_tools_lights | C11: =IF($B11="","",SUMIFS(tbl_Budget[budget_revenue],tbl_Budget[category],$B11,tbl_Budget[month],i_Setup!$C$10)) -> 600.78 | D11: =IF($B11="","",SUMIFS(tbl_Actuals[revenue],tbl_Actuals[category],$B11,tbl_Actuals[month],i_Setup!$C$10)) -> 8212.53 | E11: =IF($B11="","",D11-C11) -> 7611.75 | F11: =IF($B11="","",IF(C11=0,"",E11/C11)) -> 12.669779 | G11: =IF($B11="","",IF(E11>0,"Favorable","Unfavorable")) -> Favorable
A12: =IF(B12<>"","Revenue","") -> Revenue | B12: =IFERROR(INDEX(c_RevenuePVM!$A$2:$A$75,MATCH(ROWS($B$8:B12),c_RevenuePVM!$N$2:$N$75,0)),"") -> cool_stuff | C12: =IF($B12="","",SUMIFS(tbl_Budget[budget_revenue],tbl_Budget[category],$B12,tbl_Budget[month],i_Setup!$C$10)) -> 40177.736 | D12: =IF($B12="","",SUMIFS(tbl_Actuals[revenue],tbl_Actuals[category],$B12,tbl_Actuals[month],i_Setup!$C$10)) -> 15794.89 | E12: =IF($B12="","",D12-C12) -> -24382.846 | F12: =IF($B12="","",IF(C12=0,"",E12/C12)) -> -0.60687456 | G12: =IF($B12="","",IF(E12>0,"Favorable","Unfavorable")) -> Unfavorable
A13: =IF(B13<>"","Revenue","") -> Revenue | B13: =IFERROR(INDEX(c_RevenuePVM!$A$2:$A$75,MATCH(ROWS($B$8:B13),c_RevenuePVM!$N$2:$N$75,0)),"") -> electronics | C13: =IF($B13="","",SUMIFS(tbl_Budget[budget_revenue],tbl_Budget[category],$B13,tbl_Budget[month],i_Setup!$C$10)) -> 3139.565 | D13: =IF($B13="","",SUMIFS(tbl_Actuals[revenue],tbl_Actuals[category],$B13,tbl_Actuals[month],i_Setup!$C$10)) -> 10739.57 | E13: =IF($B13="","",D13-C13) -> 7600.005 | F13: =IF($B13="","",IF(C13=0,"",E13/C13)) -> 2.4207191 | G13: =IF($B13="","",IF(E13>0,"Favorable","Unfavorable")) -> Favorable
A14: =IF(B14<>"","Revenue","") -> Revenue | B14: =IFERROR(INDEX(c_RevenuePVM!$A$2:$A$75,MATCH(ROWS($B$8:B14),c_RevenuePVM!$N$2:$N$75,0)),"") -> food | C14: =IF($B14="","",SUMIFS(tbl_Budget[budget_revenue],tbl_Budget[category],$B14,tbl_Budget[month],i_Setup!$C$10)) -> 382.725 | D14: =IF($B14="","",SUMIFS(tbl_Actuals[revenue],tbl_Actuals[category],$B14,tbl_Actuals[month],i_Setup!$C$10)) -> 8174.18 | E14: =IF($B14="","",D14-C14) -> 7791.455 | F14: =IF($B14="","",IF(C14=0,"",E14/C14)) -> 20.357842 | G14: =IF($B14="","",IF(E14>0,"Favorable","Unfavorable")) -> Favorable
A15: =IF(B15<>"","Revenue","") -> Revenue | B15: =IFERROR(INDEX(c_RevenuePVM!$A$2:$A$75,MATCH(ROWS($B$8:B15),c_RevenuePVM!$N$2:$N$75,0)),"") -> furniture_decor | C15: =IF($B15="","",SUMIFS(tbl_Budget[budget_revenue],tbl_Budget[category],$B15,tbl_Budget[month],i_Setup!$C$10)) -> 34267.808 | D15: =IF($B15="","",SUMIFS(tbl_Actuals[revenue],tbl_Actuals[category],$B15,tbl_Actuals[month],i_Setup!$C$10)) -> 41168.55 | E15: =IF($B15="","",D15-C15) -> 6900.7422 | F15: =IF($B15="","",IF(C15=0,"",E15/C15)) -> 0.20137682 | G15: =IF($B15="","",IF(E15>0,"Favorable","Unfavorable")) -> Favorable
A16: =IF(B16<>"","Revenue","") -> Revenue | B16: =IFERROR(INDEX(c_RevenuePVM!$A$2:$A$75,MATCH(ROWS($B$8:B16),c_RevenuePVM!$N$2:$N$75,0)),"") -> garden_tools | C16: =IF($B16="","",SUMIFS(tbl_Budget[budget_revenue],tbl_Budget[category],$B16,tbl_Budget[month],i_Setup!$C$10)) -> 23379.349 | D16: =IF($B16="","",SUMIFS(tbl_Actuals[revenue],tbl_Actuals[category],$B16,tbl_Actuals[month],i_Setup!$C$10)) -> 16314.7 | E16: =IF($B16="","",D16-C16) -> -7064.6486 | F16: =IF($B16="","",IF(C16=0,"",E16/C16)) -> -0.30217474 | G16: =IF($B16="","",IF(E16>0,"Favorable","Unfavorable")) -> Unfavorable
A17: =IF(B17<>"","Revenue","") -> Revenue | B17: =IFERROR(INDEX(c_RevenuePVM!$A$2:$A$75,MATCH(ROWS($B$8:B17),c_RevenuePVM!$N$2:$N$75,0)),"") -> health_beauty | C17: =IF($B17="","",SUMIFS(tbl_Budget[budget_revenue],tbl_Budget[category],$B17,tbl_Budget[month],i_Setup!$C$10)) -> 51481.742 | D17: =IF($B17="","",SUMIFS(tbl_Actuals[revenue],tbl_Actuals[category],$B17,tbl_Actuals[month],i_Setup!$C$10)) -> 119391.01 | E17: =IF($B17="","",D17-C17) -> 67909.268 | F17: =IF($B17="","",IF(C17=0,"",E17/C17)) -> 1.3190942 | G17: =IF($B17="","",IF(E17>0,"Favorable","Unfavorable")) -> Favorable
A18: =IF(B18<>"","Revenue","") -> Revenue | B18: =IFERROR(INDEX(c_RevenuePVM!$A$2:$A$75,MATCH(ROWS($B$8:B18),c_RevenuePVM!$N$2:$N$75,0)),"") -> home_construction | C18: =IF($B18="","",SUMIFS(tbl_Budget[budget_revenue],tbl_Budget[category],$B18,tbl_Budget[month],i_Setup!$C$10)) -> 127.296 | D18: =IF($B18="","",SUMIFS(tbl_Actuals[revenue],tbl_Actuals[category],$B18,tbl_Actuals[month],i_Setup!$C$10)) -> 6286.16 | E18: =IF($B18="","",D18-C18) -> 6158.864 | F18: =IF($B18="","",IF(C18=0,"",E18/C18)) -> 48.382227 | G18: =IF($B18="","",IF(E18>0,"Favorable","Unfavorable")) -> Favorable
A19: =IF(B19<>"","Revenue","") -> Revenue | B19: =IFERROR(INDEX(c_RevenuePVM!$A$2:$A$75,MATCH(ROWS($B$8:B19),c_RevenuePVM!$N$2:$N$75,0)),"") -> housewares | C19: =IF($B19="","",SUMIFS(tbl_Budget[budget_revenue],tbl_Budget[category],$B19,tbl_Budget[month],i_Setup!$C$10)) -> 23896.397 | D19: =IF($B19="","",SUMIFS(tbl_Actuals[revenue],tbl_Actuals[category],$B19,tbl_Actuals[month],i_Setup!$C$10)) -> 58763.36 | E19: =IF($B19="","",D19-C19) -> 34866.963 | F19: =IF($B19="","",IF(C19=0,"",E19/C19)) -> 1.4590887 | G19: =IF($B19="","",IF(E19>0,"Favorable","Unfavorable")) -> Favorable
... A30: =IF(B30<>"","Revenue","") | B30: =IFERROR(INDEX(c_RevenuePVM!$A$2:$A$75,MATCH(ROWS($B$8:B30),c_RevenuePVM!$N$2:$N$75,0)),"") | C30: =IF($B30="","",SUMIFS(tbl_Budget[budget_revenue],tbl_Budget[category],$B30,tbl_Budget[month],i_Setup!$C$10)) | D30: =IF($B30="","",SUMIFS(tbl_Actuals[revenue],tbl_Actuals[category],$B30,tbl_Actuals[month],i_Setup!$C$10)) | E30: =IF($B30="","",D30-C30) | F30: =IF($B30="","",IF(C30=0,"",E30/C30)) | G30: =IF($B30="","",IF(E30>0,"Favorable","Unfavorable"))
